pyjsonrpc2/__init__.py
pyjsonrpc2/py.typed
pyjsonrpc2/server.py
pyjsonrpc2-1.0.1.dist-info/LICENSE.txt
pyjsonrpc2-1.0.1.dist-info/METADATA
pyjsonrpc2-1.0.1.dist-info/WHEEL
pyjsonrpc2-1.0.1.dist-info/top_level.txt
pyjsonrpc2-1.0.1.dist-info/RECORD
