Metadata-Version: 2.1
Name: pyjsonrpc2
Version: 1.0.1
Summary: A flexible Python implementation of the JSON-RPC 2.0 protocol.
Author-email: Crimson-Crow <github@crimsoncrow.dev>
Maintainer-email: Crimson-Crow <github@crimsoncrow.dev>
License: MIT License
Project-URL: Homepage, https://github.com/Crimson-Crow/pyjsonrpc2
Project-URL: Bug Reports, https://github.com/Crimson-Crow/pyjsonrpc2/issues
Project-URL: Source, https://github.com/Crimson-Crow/pyjsonrpc2
Keywords: jsonrpc,json-rpc,rpc,json,server,client
Classifier: Development Status :: 4 - Beta
Classifier: Intended Audience :: Developers
Classifier: License :: OSI Approved :: MIT License
Classifier: Programming Language :: Python :: 3
Classifier: Programming Language :: Python :: 3.8
Classifier: Programming Language :: Python :: 3.9
Classifier: Programming Language :: Python :: 3.10
Classifier: Programming Language :: Python :: 3.11
Classifier: Programming Language :: Python :: 3.12
Classifier: Programming Language :: Python :: 3.13
Classifier: Programming Language :: Python :: 3 :: Only
Classifier: Typing :: Typed
Requires-Python: >=3.8
License-File: LICENSE.txt
Requires-Dist: orjson
